ground/__init__.py
ground/context.py
ground/enums.py
ground/hints.py
ground/py.typed
ground/_core/__init__.py
ground/_core/boxed.py
ground/_core/discrete.py
ground/_core/enums.py
ground/_core/geometries.py
ground/_core/hints.py
ground/_core/packing.py
ground/_core/primitive.py
ground/_core/angular/__init__.py
ground/_core/angular/context.py
ground/_core/angular/plain/__init__.py
ground/_core/angular/plain/kind.py
ground/_core/angular/plain/orientation.py
ground/_core/centroidal/__init__.py
ground/_core/centroidal/context.py
ground/_core/centroidal/plain/__init__.py
ground/_core/centroidal/plain/contour.py
ground/_core/centroidal/plain/multipoint.py
ground/_core/centroidal/plain/multipolygon.py
ground/_core/centroidal/plain/multisegment.py
ground/_core/centroidal/plain/polygon.py
ground/_core/centroidal/plain/region.py
ground/_core/centroidal/plain/segment.py
ground/_core/circular/__init__.py
ground/_core/circular/context.py
ground/_core/circular/plain/__init__.py
ground/_core/circular/plain/point_point_point.py
ground/_core/measured/__init__.py
ground/_core/measured/context.py
ground/_core/measured/plain/__init__.py
ground/_core/measured/plain/region.py
ground/_core/metric/__init__.py
ground/_core/metric/context.py
ground/_core/metric/plain/__init__.py
ground/_core/metric/plain/box.py
ground/_core/metric/plain/point.py
ground/_core/metric/plain/segment.py
ground/_core/rotation/__init__.py
ground/_core/rotation/context.py
ground/_core/rotation/plain.py
ground/_core/scaling/__init__.py
ground/_core/scaling/context.py
ground/_core/scaling/plain.py
ground/_core/segment/__init__.py
ground/_core/segment/context.py
ground/_core/segment/plain.py
ground/_core/translation/__init__.py
ground/_core/translation/context.py
ground/_core/translation/plain.py
ground/_core/vector/__init__.py
ground/_core/vector/context.py
ground/_core/vector/plain/__init__.py
ground/_core/vector/plain/cross.py
ground/_core/vector/plain/dot.py
ground-12.0.0.dist-info/licenses/LICENSE
ground-12.0.0.dist-info/METADATA
ground-12.0.0.dist-info/WHEEL
ground-12.0.0.dist-info/top_level.txt
ground-12.0.0.dist-info/RECORD
